slackchat/__init__.py
slackchat/admin.py
slackchat/apps.py
slackchat/authentication.py
slackchat/celery.py
slackchat/conf.py
slackchat/exceptions.py
slackchat/fields.py
slackchat/signals.py
slackchat/urls.py
slackchat/utils.py
slackchat/views.py
slackchat/viewsets.py
slackchat/widgets.py
slackchat/handlers/__init__.py
slackchat/handlers/attachments.py
slackchat/handlers/messages.py
slackchat/handlers/reactions.py
slackchat/management/__init__.py
slackchat/management/commands/__init__.py
slackchat/management/commands/get_slackchat_users.py
slackchat/migrations/0001_initial.py
slackchat/migrations/0002_auto_20180414_2144.py
slackchat/migrations/0003_auto_20180507_1315.py
slackchat/migrations/0004_auto_20181015_2032.py
slackchat/migrations/0005_auto_20181015_2207.py
slackchat/migrations/0006_auto_20181101_2045.py
slackchat/migrations/0007_message_serialized.py
slackchat/migrations/0008_auto_20190219_1745.py
slackchat/migrations/0009_auto_20190219_2026.py
slackchat/migrations/0010_auto_20200401_2133.py
slackchat/migrations/__init__.py
slackchat/models/__init__.py
slackchat/models/argument.py
slackchat/models/attachment.py
slackchat/models/channel.py
slackchat/models/chat_type.py
slackchat/models/custom_content_template.py
slackchat/models/keyword_argument.py
slackchat/models/message.py
slackchat/models/reaction.py
slackchat/models/user.py
slackchat/models/webhook.py
slackchat/serializers/__init__.py
slackchat/serializers/attachment.py
slackchat/serializers/channel.py
slackchat/serializers/chat_type.py
slackchat/serializers/message.py
slackchat/serializers/mixins.py
slackchat/serializers/reaction.py
slackchat/serializers/user.py
slackchat/serializers/webhook.py
slackchat/static/.DS_Store
slackchat/static/slackchat/stats.html
slackchat/static/slackchat/css/editor.css
slackchat/static/slackchat/css/main.detail.css
slackchat/static/slackchat/css/main.list.css
slackchat/static/slackchat/js/editor.js
slackchat/static/slackchat/js/main.detail.js
django_slackchat_serializer-1.1.2.dist-info/LICENSE
django_slackchat_serializer-1.1.2.dist-info/METADATA
django_slackchat_serializer-1.1.2.dist-info/WHEEL
django_slackchat_serializer-1.1.2.dist-info/top_level.txt
django_slackchat_serializer-1.1.2.dist-info/RECORD
