Metadata-Version: 2.1
Name: django-slackchat-serializer
Version: 1.1.2
Summary: A Django app that serializes conversations in Slack.
Home-page: https://github.com/The-Politico/django-slackchat-serializer
License: MIT
Platform: UNKNOWN
Classifier: Environment :: Web Environment
Classifier: Framework :: Django
Classifier: Intended Audience :: Developers
Classifier: Operating System :: OS Independent
Classifier: Programming Language :: Python
Classifier: Programming Language :: Python :: 3
Classifier: Programming Language :: Python :: 3.4
Classifier: Programming Language :: Python :: 3.5
Classifier: Programming Language :: Python :: 3.6
Classifier: Topic :: Internet :: WWW/HTTP
Classifier: Topic :: Internet :: WWW/HTTP :: Dynamic Content
Requires-Python: >=3
Requires-Dist: celery
Requires-Dist: djangorestframework
Requires-Dist: django-foreignform
Requires-Dist: emoji
Requires-Dist: markdown
Requires-Dist: markslack
Requires-Dist: Pillow
Requires-Dist: slackclient (<2,>=1)
Requires-Dist: slacker
Requires-Dist: tqdm
